{"cameraMode":{"drawMode":0,"name":"Shaded","section":"Shading Mode"},"sceneLighting":true,"audioPlay":false,"sceneViewState":{"m_AlwaysRefresh":true,"showFog":false,"showSkybox":false,"showFlares":false,"showImageEffects":false,"showParticleSystems":false,"showVisualEffectGraphs":true,"m_FxEnabled":true},"in2DMode":false,"pivot":{"x":2.7975220680236818,"y":-1.8316926956176758,"z":-6.786576271057129},"rotation":{"x":-0.0406123548746109,"y":-0.9558774828910828,"z":0.1594787836074829,"w":-0.2436479777097702},"size":6.3572845458984379,"orthographic":false}